{
"type": "FeatureCollection",
"crs": { "type": "name", "properties": { "name": "urn:ogc:def:crs:OGC:1.3:CRS84" } },
"features": [
{ "type": "Feature", "id": 17713, "properties": { "SERVICE.REQUEST.TYPE": "Vacant\/Abandoned Building", "SERVICE.REQUEST.NUMBER": "11-03713708", "DATE.SERVICE.REQUEST.WAS.RECEIVED": "2011-09-02", "LOCATION.OF.BUILDING.ON.THE.LOT..IF.GARAGE..CHANGE.TYPE.CODE.TO.BGD..": "", "IS.THE.BUILDING.DANGEROUS.OR.HAZARDOUS.": "", "IS.BUILDING.OPEN.OR.BOARDED.": "", "IF.THE.BUILDING.IS.OPEN..WHERE.IS.THE.ENTRY.POINT.": "", "IS.THE.BUILDING.CURRENTLY.VACANT.OR.OCCUPIED.": "", "IS.THE.BUILDING.VACANT.DUE.TO.FIRE.": "", "ANY.PEOPLE.USING.PROPERTY...HOMELESS..CHILDEN..GANGS.": "", "ADDRESS.STREET.NUMBER": "3818", "ADDRESS.STREET.DIRECTION": "N", "ADDRESS.STREET.NAME": "KENNETH", "ADDRESS.STREET.SUFFIX": "AVE", "ZIP.CODE": 60641, "Ward": 38, "Police.District": 17, "Community.Area": 16, "FULL_ADDR": "3818 N KENNETH AVE", "HOUSE_LOW": 3818, "HOUSE_HIGH": 3818, "PRE": "N", "STREET_NAME": "KENNETH", "STREET_TYPE": "AVE", "SUFDIR": " ", "XCOORD": 1145754.4863101498, "YCOORD": 1925103.9350230554, "STATUS1": "VALID", "STATUS2": "ACTUAL", "longitude": -87.739619040446186, "latitude": 41.950479372798839 }, "geometry": { "type": "Point", "coordinates": [ -87.739619040446186, 41.950479372798839 ] } },
{ "type": "Feature", "id": 25406, "properties": { "SERVICE.REQUEST.TYPE": "Vacant\/Abandoned Building", "SERVICE.REQUEST.NUMBER": "12-00787239", "DATE.SERVICE.REQUEST.WAS.RECEIVED": "2012-04-19", "LOCATION.OF.BUILDING.ON.THE.LOT..IF.GARAGE..CHANGE.TYPE.CODE.TO.BGD..": "", "IS.THE.BUILDING.DANGEROUS.OR.HAZARDOUS.": "", "IS.BUILDING.OPEN.OR.BOARDED.": "", "IF.THE.BUILDING.IS.OPEN..WHERE.IS.THE.ENTRY.POINT.": "", "IS.THE.BUILDING.CURRENTLY.VACANT.OR.OCCUPIED.": "", "IS.THE.BUILDING.VACANT.DUE.TO.FIRE.": "", "ANY.PEOPLE.USING.PROPERTY...HOMELESS..CHILDEN..GANGS.": "", "ADDRESS.STREET.NUMBER": "3942", "ADDRESS.STREET.DIRECTION": "N", "ADDRESS.STREET.NAME": "LOWELL", "ADDRESS.STREET.SUFFIX": "AVE", "ZIP.CODE": 60641, "Ward": 38, "Police.District": 17, "Community.Area": 16, "FULL_ADDR": "3942 N LOWELL AVE", "HOUSE_LOW": 3942, "HOUSE_HIGH": 3942, "PRE": "N", "STREET_NAME": "LOWELL", "STREET_TYPE": "AVE", "SUFDIR": " ", "XCOORD": 1146479.6048486098, "YCOORD": 1926027.662523292, "STATUS1": "VALID", "STATUS2": "ACTUAL", "longitude": -87.736929907677947, "latitude": 41.953000342485659 }, "geometry": { "type": "Point", "coordinates": [ -87.736929907677947, 41.953000342485659 ] } }
]
}
