{
"type": "FeatureCollection",
"crs": { "type": "name", "properties": { "name": "urn:ogc:def:crs:OGC:1.3:CRS84" } },
"features": [
{ "type": "Feature", "id": 23546, "properties": { "SERVICE.REQUEST.TYPE": "Vacant\/Abandoned Building", "SERVICE.REQUEST.NUMBER": "12-00491923", "DATE.SERVICE.REQUEST.WAS.RECEIVED": "2012-02-27", "LOCATION.OF.BUILDING.ON.THE.LOT..IF.GARAGE..CHANGE.TYPE.CODE.TO.BGD..": "Front", "IS.THE.BUILDING.DANGEROUS.OR.HAZARDOUS.": "", "IS.BUILDING.OPEN.OR.BOARDED.": "Open", "IF.THE.BUILDING.IS.OPEN..WHERE.IS.THE.ENTRY.POINT.": "", "IS.THE.BUILDING.CURRENTLY.VACANT.OR.OCCUPIED.": "Vacant", "IS.THE.BUILDING.VACANT.DUE.TO.FIRE.": "false", "ANY.PEOPLE.USING.PROPERTY...HOMELESS..CHILDEN..GANGS.": "false", "ADDRESS.STREET.NUMBER": "1915", "ADDRESS.STREET.DIRECTION": "W", "ADDRESS.STREET.NAME": "GRANVILLE", "ADDRESS.STREET.SUFFIX": "AVE", "ZIP.CODE": 60660, "Ward": 40, "Police.District": 24, "Community.Area": 2, "FULL_ADDR": "1915 W GRANVILLE AVE", "HOUSE_LOW": 1915, "HOUSE_HIGH": 1915, "PRE": "W", "STREET_NAME": "GRANVILLE", "STREET_TYPE": "AVE", "SUFDIR": " ", "XCOORD": 1162436.3048818361, "YCOORD": 1941154.9613034229, "STATUS1": "VALID", "STATUS2": "ACTUAL", "longitude": -87.67784646417131, "latitude": 41.994190579893832 }, "geometry": { "type": "Point", "coordinates": [ -87.67784646417131, 41.994190579893832 ] } },
{ "type": "Feature", "id": 28803, "properties": { "SERVICE.REQUEST.TYPE": "Vacant\/Abandoned Building", "SERVICE.REQUEST.NUMBER": "12-01361853", "DATE.SERVICE.REQUEST.WAS.RECEIVED": "2012-07-30", "LOCATION.OF.BUILDING.ON.THE.LOT..IF.GARAGE..CHANGE.TYPE.CODE.TO.BGD..": "", "IS.THE.BUILDING.DANGEROUS.OR.HAZARDOUS.": "", "IS.BUILDING.OPEN.OR.BOARDED.": "", "IF.THE.BUILDING.IS.OPEN..WHERE.IS.THE.ENTRY.POINT.": "", "IS.THE.BUILDING.CURRENTLY.VACANT.OR.OCCUPIED.": "", "IS.THE.BUILDING.VACANT.DUE.TO.FIRE.": "", "ANY.PEOPLE.USING.PROPERTY...HOMELESS..CHILDEN..GANGS.": "", "ADDRESS.STREET.NUMBER": "6128", "ADDRESS.STREET.DIRECTION": "N", "ADDRESS.STREET.NAME": "WOLCOTT", "ADDRESS.STREET.SUFFIX": "AVE", "ZIP.CODE": 60660, "Ward": 40, "Police.District": 24, "Community.Area": 2, "FULL_ADDR": "6128 N WOLCOTT AVE", "HOUSE_LOW": 6128, "HOUSE_HIGH": 6128, "PRE": "N", "STREET_NAME": "WOLCOTT", "STREET_TYPE": "AVE", "SUFDIR": " ", "XCOORD": 1162594.305940093, "YCOORD": 1940660.404834687, "STATUS1": "VALID", "STATUS2": "ACTUAL", "longitude": -87.677279205810791, "latitude": 41.992830181328813 }, "geometry": { "type": "Point", "coordinates": [ -87.677279205810791, 41.992830181328813 ] } },
{ "type": "Feature", "id": 30014, "properties": { "SERVICE.REQUEST.TYPE": "Vacant\/Abandoned Building", "SERVICE.REQUEST.NUMBER": "12-01576485", "DATE.SERVICE.REQUEST.WAS.RECEIVED": "2012-09-06", "LOCATION.OF.BUILDING.ON.THE.LOT..IF.GARAGE..CHANGE.TYPE.CODE.TO.BGD..": "Front", "IS.THE.BUILDING.DANGEROUS.OR.HAZARDOUS.": "", "IS.BUILDING.OPEN.OR.BOARDED.": "Open", "IF.THE.BUILDING.IS.OPEN..WHERE.IS.THE.ENTRY.POINT.": "", "IS.THE.BUILDING.CURRENTLY.VACANT.OR.OCCUPIED.": "Vacant", "IS.THE.BUILDING.VACANT.DUE.TO.FIRE.": "false", "ANY.PEOPLE.USING.PROPERTY...HOMELESS..CHILDEN..GANGS.": "true", "ADDRESS.STREET.NUMBER": "1903", "ADDRESS.STREET.DIRECTION": "W", "ADDRESS.STREET.NAME": "HOOD", "ADDRESS.STREET.SUFFIX": "AVE", "ZIP.CODE": 60660, "Ward": 40, "Police.District": 24, "Community.Area": 2, "FULL_ADDR": "1903 W HOOD AVE", "HOUSE_LOW": 1903, "HOUSE_HIGH": 1903, "PRE": "W", "STREET_NAME": "HOOD", "STREET_TYPE": "AVE", "SUFDIR": " ", "XCOORD": 1162590.6043408096, "YCOORD": 1940729.7363197268, "STATUS1": "VALID", "STATUS2": "ACTUAL", "longitude": -87.677290867860307, "latitude": 41.99302050691977 }, "geometry": { "type": "Point", "coordinates": [ -87.677290867860307, 41.99302050691977 ] } },
{ "type": "Feature", "id": 33617, "properties": { "SERVICE.REQUEST.TYPE": "Vacant\/Abandoned Building", "SERVICE.REQUEST.NUMBER": "13-00287018", "DATE.SERVICE.REQUEST.WAS.RECEIVED": "2013-03-14", "LOCATION.OF.BUILDING.ON.THE.LOT..IF.GARAGE..CHANGE.TYPE.CODE.TO.BGD..": "", "IS.THE.BUILDING.DANGEROUS.OR.HAZARDOUS.": "", "IS.BUILDING.OPEN.OR.BOARDED.": "", "IF.THE.BUILDING.IS.OPEN..WHERE.IS.THE.ENTRY.POINT.": "", "IS.THE.BUILDING.CURRENTLY.VACANT.OR.OCCUPIED.": "", "IS.THE.BUILDING.VACANT.DUE.TO.FIRE.": "", "ANY.PEOPLE.USING.PROPERTY...HOMELESS..CHILDEN..GANGS.": "", "ADDRESS.STREET.NUMBER": "6090", "ADDRESS.STREET.DIRECTION": "N", "ADDRESS.STREET.NAME": "RIDGE", "ADDRESS.STREET.SUFFIX": "AVE", "ZIP.CODE": 60660, "Ward": 40, "Police.District": 24, "Community.Area": 2, "FULL_ADDR": "6090 N RIDGE AVE", "HOUSE_LOW": 6090, "HOUSE_HIGH": 6090, "PRE": "N", "STREET_NAME": "RIDGE", "STREET_TYPE": "AVE", "SUFDIR": " ", "XCOORD": 1163212.2199672796, "YCOORD": 1940371.2033749828, "STATUS1": "VALID", "STATUS2": "ACTUAL", "longitude": -87.675014480976941, "latitude": 41.99202359137746 }, "geometry": { "type": "Point", "coordinates": [ -87.675014480976941, 41.99202359137746 ] } }
]
}
