{
"type": "FeatureCollection",
"crs": { "type": "name", "properties": { "name": "urn:ogc:def:crs:OGC:1.3:CRS84" } },
"features": [
{ "type": "Feature", "id": 21435, "properties": { "SERVICE.REQUEST.TYPE": "Vacant\/Abandoned Building", "SERVICE.REQUEST.NUMBER": "11-04234745", "DATE.SERVICE.REQUEST.WAS.RECEIVED": "2011-12-09", "LOCATION.OF.BUILDING.ON.THE.LOT..IF.GARAGE..CHANGE.TYPE.CODE.TO.BGD..": "Garage", "IS.THE.BUILDING.DANGEROUS.OR.HAZARDOUS.": "", "IS.BUILDING.OPEN.OR.BOARDED.": "Boarded", "IF.THE.BUILDING.IS.OPEN..WHERE.IS.THE.ENTRY.POINT.": "DOORS ARE CLOSED", "IS.THE.BUILDING.CURRENTLY.VACANT.OR.OCCUPIED.": "Vacant", "IS.THE.BUILDING.VACANT.DUE.TO.FIRE.": "false", "ANY.PEOPLE.USING.PROPERTY...HOMELESS..CHILDEN..GANGS.": "false", "ADDRESS.STREET.NUMBER": "1352", "ADDRESS.STREET.DIRECTION": "W", "ADDRESS.STREET.NAME": "TAYLOR", "ADDRESS.STREET.SUFFIX": "ST", "ZIP.CODE": 60607, "Ward": 25, "Police.District": 12, "Community.Area": 28, "FULL_ADDR": "1352 W TAYLOR ST", "HOUSE_LOW": 1352, "HOUSE_HIGH": 1352, "PRE": "W", "STREET_NAME": "TAYLOR", "STREET_TYPE": "ST", "SUFDIR": " ", "XCOORD": 1167280.1429808566, "YCOORD": 1895735.4373871065, "STATUS1": "VALID", "STATUS2": "ACTUAL", "longitude": -87.661338292045414, "latitude": 41.869453939942055 }, "geometry": { "type": "Point", "coordinates": [ -87.661338292045414, 41.869453939942055 ] } },
{ "type": "Feature", "id": 24464, "properties": { "SERVICE.REQUEST.TYPE": "Vacant\/Abandoned Building", "SERVICE.REQUEST.NUMBER": "12-00656615", "DATE.SERVICE.REQUEST.WAS.RECEIVED": "2012-03-22", "LOCATION.OF.BUILDING.ON.THE.LOT..IF.GARAGE..CHANGE.TYPE.CODE.TO.BGD..": "", "IS.THE.BUILDING.DANGEROUS.OR.HAZARDOUS.": "", "IS.BUILDING.OPEN.OR.BOARDED.": "", "IF.THE.BUILDING.IS.OPEN..WHERE.IS.THE.ENTRY.POINT.": "", "IS.THE.BUILDING.CURRENTLY.VACANT.OR.OCCUPIED.": "", "IS.THE.BUILDING.VACANT.DUE.TO.FIRE.": "", "ANY.PEOPLE.USING.PROPERTY...HOMELESS..CHILDEN..GANGS.": "", "ADDRESS.STREET.NUMBER": "1352", "ADDRESS.STREET.DIRECTION": "W", "ADDRESS.STREET.NAME": "TAYLOR", "ADDRESS.STREET.SUFFIX": "ST", "ZIP.CODE": 60607, "Ward": 25, "Police.District": 12, "Community.Area": 28, "FULL_ADDR": "1352 W TAYLOR ST", "HOUSE_LOW": 1352, "HOUSE_HIGH": 1352, "PRE": "W", "STREET_NAME": "TAYLOR", "STREET_TYPE": "ST", "SUFDIR": " ", "XCOORD": 1167280.1429808566, "YCOORD": 1895735.4373871065, "STATUS1": "VALID", "STATUS2": "ACTUAL", "longitude": -87.661338292045414, "latitude": 41.869453939942055 }, "geometry": { "type": "Point", "coordinates": [ -87.661338292045414, 41.869453939942055 ] } },
{ "type": "Feature", "id": 57680, "properties": { "SERVICE.REQUEST.TYPE": "Vacant\/Abandoned Building", "SERVICE.REQUEST.NUMBER": "17-01282701", "DATE.SERVICE.REQUEST.WAS.RECEIVED": "2017-03-08", "LOCATION.OF.BUILDING.ON.THE.LOT..IF.GARAGE..CHANGE.TYPE.CODE.TO.BGD..": "Front", "IS.THE.BUILDING.DANGEROUS.OR.HAZARDOUS.": "", "IS.BUILDING.OPEN.OR.BOARDED.": "Boarded", "IF.THE.BUILDING.IS.OPEN..WHERE.IS.THE.ENTRY.POINT.": "", "IS.THE.BUILDING.CURRENTLY.VACANT.OR.OCCUPIED.": "Vacant", "IS.THE.BUILDING.VACANT.DUE.TO.FIRE.": "false", "ANY.PEOPLE.USING.PROPERTY...HOMELESS..CHILDEN..GANGS.": "false", "ADDRESS.STREET.NUMBER": "1158", "ADDRESS.STREET.DIRECTION": "S", "ADDRESS.STREET.NAME": "RACINE", "ADDRESS.STREET.SUFFIX": "AVE", "ZIP.CODE": 60607, "Ward": 28, "Police.District": 12, "Community.Area": 28, "FULL_ADDR": "1140 S RACINE AVE", "HOUSE_LOW": 1140, "HOUSE_HIGH": 1140, "PRE": "S", "STREET_NAME": "RACINE", "STREET_TYPE": "AVE", "SUFDIR": " ", "XCOORD": 1168515.214497023, "YCOORD": 1894863.9058784405, "STATUS1": "VALID", "STATUS2": "LOGICAL", "longitude": -87.656829247179573, "latitude": 41.867035766888947 }, "geometry": { "type": "Point", "coordinates": [ -87.656829247179573, 41.867035766888947 ] } }
]
}
