{
"type": "FeatureCollection",
"crs": { "type": "name", "properties": { "name": "urn:ogc:def:crs:OGC:1.3:CRS84" } },
"features": [
{ "type": "Feature", "id": 24173, "properties": { "SERVICE.REQUEST.TYPE": "Vacant\/Abandoned Building", "SERVICE.REQUEST.NUMBER": "12-00617674", "DATE.SERVICE.REQUEST.WAS.RECEIVED": "2012-03-15", "LOCATION.OF.BUILDING.ON.THE.LOT..IF.GARAGE..CHANGE.TYPE.CODE.TO.BGD..": "", "IS.THE.BUILDING.DANGEROUS.OR.HAZARDOUS.": "", "IS.BUILDING.OPEN.OR.BOARDED.": "", "IF.THE.BUILDING.IS.OPEN..WHERE.IS.THE.ENTRY.POINT.": "", "IS.THE.BUILDING.CURRENTLY.VACANT.OR.OCCUPIED.": "", "IS.THE.BUILDING.VACANT.DUE.TO.FIRE.": "", "ANY.PEOPLE.USING.PROPERTY...HOMELESS..CHILDEN..GANGS.": "", "ADDRESS.STREET.NUMBER": "4740", "ADDRESS.STREET.DIRECTION": "N", "ADDRESS.STREET.NAME": "HERMITAGE", "ADDRESS.STREET.SUFFIX": "AVE", "ZIP.CODE": 60640, "Ward": 47, "Police.District": 19, "Community.Area": 3, "FULL_ADDR": "4740 N HERMITAGE AVE", "HOUSE_LOW": 4740, "HOUSE_HIGH": 4740, "PRE": "N", "STREET_NAME": "HERMITAGE", "STREET_TYPE": "AVE", "SUFDIR": " ", "XCOORD": 1163899.9911798055, "YCOORD": 1931708.5609570728, "STATUS1": "VALID", "STATUS2": "ACTUAL", "longitude": -87.672730393833604, "latitude": 41.968238461260825 }, "geometry": { "type": "Point", "coordinates": [ -87.672730393833604, 41.968238461260825 ] } },
{ "type": "Feature", "id": 27703, "properties": { "SERVICE.REQUEST.TYPE": "Vacant\/Abandoned Building", "SERVICE.REQUEST.NUMBER": "12-01284098", "DATE.SERVICE.REQUEST.WAS.RECEIVED": "2012-07-18", "LOCATION.OF.BUILDING.ON.THE.LOT..IF.GARAGE..CHANGE.TYPE.CODE.TO.BGD..": "", "IS.THE.BUILDING.DANGEROUS.OR.HAZARDOUS.": "", "IS.BUILDING.OPEN.OR.BOARDED.": "", "IF.THE.BUILDING.IS.OPEN..WHERE.IS.THE.ENTRY.POINT.": "", "IS.THE.BUILDING.CURRENTLY.VACANT.OR.OCCUPIED.": "", "IS.THE.BUILDING.VACANT.DUE.TO.FIRE.": "", "ANY.PEOPLE.USING.PROPERTY...HOMELESS..CHILDEN..GANGS.": "", "ADDRESS.STREET.NUMBER": "4619", "ADDRESS.STREET.DIRECTION": "N", "ADDRESS.STREET.NAME": "ASHLAND", "ADDRESS.STREET.SUFFIX": "AVE", "ZIP.CODE": 60640, "Ward": 47, "Police.District": 19, "Community.Area": 3, "FULL_ADDR": "4619 N ASHLAND AVE", "HOUSE_LOW": 4619, "HOUSE_HIGH": 4619, "PRE": "N", "STREET_NAME": "ASHLAND", "STREET_TYPE": "AVE", "SUFDIR": " ", "XCOORD": 1164862.7571815918, "YCOORD": 1930833.7082949912, "STATUS1": "VALID", "STATUS2": "ACTUAL", "longitude": -87.6692153062518, "latitude": 41.965817406456225 }, "geometry": { "type": "Point", "coordinates": [ -87.6692153062518, 41.965817406456225 ] } },
{ "type": "Feature", "id": 38621, "properties": { "SERVICE.REQUEST.TYPE": "Vacant\/Abandoned Building", "SERVICE.REQUEST.NUMBER": "13-01367857", "DATE.SERVICE.REQUEST.WAS.RECEIVED": "2013-09-17", "LOCATION.OF.BUILDING.ON.THE.LOT..IF.GARAGE..CHANGE.TYPE.CODE.TO.BGD..": "Front", "IS.THE.BUILDING.DANGEROUS.OR.HAZARDOUS.": "", "IS.BUILDING.OPEN.OR.BOARDED.": "Open", "IF.THE.BUILDING.IS.OPEN..WHERE.IS.THE.ENTRY.POINT.": "", "IS.THE.BUILDING.CURRENTLY.VACANT.OR.OCCUPIED.": "Vacant", "IS.THE.BUILDING.VACANT.DUE.TO.FIRE.": "false", "ANY.PEOPLE.USING.PROPERTY...HOMELESS..CHILDEN..GANGS.": "true", "ADDRESS.STREET.NUMBER": "4714", "ADDRESS.STREET.DIRECTION": "N", "ADDRESS.STREET.NAME": "ASHLAND", "ADDRESS.STREET.SUFFIX": "AVE", "ZIP.CODE": 60640, "Ward": 47, "Police.District": 19, "Community.Area": 3, "FULL_ADDR": "4714 N ASHLAND AVE", "HOUSE_LOW": 4714, "HOUSE_HIGH": 4714, "PRE": "N", "STREET_NAME": "ASHLAND", "STREET_TYPE": "AVE", "SUFDIR": " ", "XCOORD": 1164765.0491315802, "YCOORD": 1931459.8412052852, "STATUS1": "VALID", "STATUS2": "ACTUAL", "longitude": -87.669556722654107, "latitude": 41.967537617703059 }, "geometry": { "type": "Point", "coordinates": [ -87.669556722654107, 41.967537617703059 ] } }
]
}
