{
"type": "FeatureCollection",
"crs": { "type": "name", "properties": { "name": "urn:ogc:def:crs:OGC:1.3:CRS84" } },
"features": [
{ "type": "Feature", "id": 3663, "properties": { "SERVICE.REQUEST.TYPE": "Vacant\/Abandoned Building", "SERVICE.REQUEST.NUMBER": "10-01309909", "DATE.SERVICE.REQUEST.WAS.RECEIVED": "2010-08-17", "LOCATION.OF.BUILDING.ON.THE.LOT..IF.GARAGE..CHANGE.TYPE.CODE.TO.BGD..": "", "IS.THE.BUILDING.DANGEROUS.OR.HAZARDOUS.": "", "IS.BUILDING.OPEN.OR.BOARDED.": "", "IF.THE.BUILDING.IS.OPEN..WHERE.IS.THE.ENTRY.POINT.": "", "IS.THE.BUILDING.CURRENTLY.VACANT.OR.OCCUPIED.": "", "IS.THE.BUILDING.VACANT.DUE.TO.FIRE.": "", "ANY.PEOPLE.USING.PROPERTY...HOMELESS..CHILDEN..GANGS.": "", "ADDRESS.STREET.NUMBER": "2443", "ADDRESS.STREET.DIRECTION": "W", "ADDRESS.STREET.NAME": "WILSON", "ADDRESS.STREET.SUFFIX": "AVE", "ZIP.CODE": 60625, "Ward": 47, "Police.District": 19, "Community.Area": 4, "FULL_ADDR": "2443 W WILSON AVE", "HOUSE_LOW": 2443, "HOUSE_HIGH": 2443, "PRE": "W", "STREET_NAME": "WILSON", "STREET_TYPE": "AVE", "SUFDIR": " ", "XCOORD": 1159078.5282620713, "YCOORD": 1930394.3783639662, "STATUS1": "VALID", "STATUS2": "ACTUAL", "longitude": -87.69049487808104, "latitude": 41.964732919858477 }, "geometry": { "type": "Point", "coordinates": [ -87.69049487808104, 41.964732919858477 ] } },
{ "type": "Feature", "id": 23506, "properties": { "SERVICE.REQUEST.TYPE": "Vacant\/Abandoned Building", "SERVICE.REQUEST.NUMBER": "12-00391487", "DATE.SERVICE.REQUEST.WAS.RECEIVED": "2012-02-24", "LOCATION.OF.BUILDING.ON.THE.LOT..IF.GARAGE..CHANGE.TYPE.CODE.TO.BGD..": "", "IS.THE.BUILDING.DANGEROUS.OR.HAZARDOUS.": "", "IS.BUILDING.OPEN.OR.BOARDED.": "", "IF.THE.BUILDING.IS.OPEN..WHERE.IS.THE.ENTRY.POINT.": "", "IS.THE.BUILDING.CURRENTLY.VACANT.OR.OCCUPIED.": "", "IS.THE.BUILDING.VACANT.DUE.TO.FIRE.": "", "ANY.PEOPLE.USING.PROPERTY...HOMELESS..CHILDEN..GANGS.": "", "ADDRESS.STREET.NUMBER": "2619", "ADDRESS.STREET.DIRECTION": "W", "ADDRESS.STREET.NAME": "AGATITE", "ADDRESS.STREET.SUFFIX": "AVE", "ZIP.CODE": 60625, "Ward": 47, "Police.District": 19, "Community.Area": 4, "FULL_ADDR": "2619 W AGATITE AVE", "HOUSE_LOW": 2619, "HOUSE_HIGH": 2619, "PRE": "W", "STREET_NAME": "AGATITE", "STREET_TYPE": "AVE", "SUFDIR": " ", "XCOORD": 1158024.2996245702, "YCOORD": 1929419.6297871075, "STATUS1": "VALID", "STATUS2": "ACTUAL", "longitude": -87.69439773137421, "latitude": 41.962079794772194 }, "geometry": { "type": "Point", "coordinates": [ -87.69439773137421, 41.962079794772194 ] } },
{ "type": "Feature", "id": 25733, "properties": { "SERVICE.REQUEST.TYPE": "Vacant\/Abandoned Building", "SERVICE.REQUEST.NUMBER": "12-00836364", "DATE.SERVICE.REQUEST.WAS.RECEIVED": "2012-04-30", "LOCATION.OF.BUILDING.ON.THE.LOT..IF.GARAGE..CHANGE.TYPE.CODE.TO.BGD..": "Front", "IS.THE.BUILDING.DANGEROUS.OR.HAZARDOUS.": "", "IS.BUILDING.OPEN.OR.BOARDED.": "Boarded", "IF.THE.BUILDING.IS.OPEN..WHERE.IS.THE.ENTRY.POINT.": "", "IS.THE.BUILDING.CURRENTLY.VACANT.OR.OCCUPIED.": "Vacant", "IS.THE.BUILDING.VACANT.DUE.TO.FIRE.": "false", "ANY.PEOPLE.USING.PROPERTY...HOMELESS..CHILDEN..GANGS.": "false", "ADDRESS.STREET.NUMBER": "4522", "ADDRESS.STREET.DIRECTION": "N", "ADDRESS.STREET.NAME": "ARTESIAN", "ADDRESS.STREET.SUFFIX": "AVE", "ZIP.CODE": 60625, "Ward": 47, "Police.District": 19, "Community.Area": 4, "FULL_ADDR": "4522 N ARTESIAN AVE", "HOUSE_LOW": 4522, "HOUSE_HIGH": 4522, "PRE": "N", "STREET_NAME": "ARTESIAN", "STREET_TYPE": "AVE", "SUFDIR": " ", "XCOORD": 1159180.4747534213, "YCOORD": 1930071.1906523986, "STATUS1": "VALID", "STATUS2": "ACTUAL", "longitude": -87.690128967331532, "latitude": 41.963843976476895 }, "geometry": { "type": "Point", "coordinates": [ -87.690128967331532, 41.963843976476895 ] } },
{ "type": "Feature", "id": 49210, "properties": { "SERVICE.REQUEST.TYPE": "Vacant\/Abandoned Building", "SERVICE.REQUEST.NUMBER": "15-02808454", "DATE.SERVICE.REQUEST.WAS.RECEIVED": "2015-06-18", "LOCATION.OF.BUILDING.ON.THE.LOT..IF.GARAGE..CHANGE.TYPE.CODE.TO.BGD..": "Front", "IS.THE.BUILDING.DANGEROUS.OR.HAZARDOUS.": "", "IS.BUILDING.OPEN.OR.BOARDED.": "Open", "IF.THE.BUILDING.IS.OPEN..WHERE.IS.THE.ENTRY.POINT.": "ALL", "IS.THE.BUILDING.CURRENTLY.VACANT.OR.OCCUPIED.": "Vacant", "IS.THE.BUILDING.VACANT.DUE.TO.FIRE.": "false", "ANY.PEOPLE.USING.PROPERTY...HOMELESS..CHILDEN..GANGS.": "false", "ADDRESS.STREET.NUMBER": "2419", "ADDRESS.STREET.DIRECTION": "W", "ADDRESS.STREET.NAME": "WILSON", "ADDRESS.STREET.SUFFIX": "AVE", "ZIP.CODE": 60625, "Ward": 47, "Police.District": 19, "Community.Area": 4, "FULL_ADDR": "2419 W WILSON AVE", "HOUSE_LOW": 2419, "HOUSE_HIGH": 2419, "PRE": "W", "STREET_NAME": "WILSON", "STREET_TYPE": "AVE", "SUFDIR": " ", "XCOORD": 1159319.0000754956, "YCOORD": 1930398.7178787163, "STATUS1": "VALID", "STATUS2": "ACTUAL", "longitude": -87.689610605542356, "latitude": 41.964739873592166 }, "geometry": { "type": "Point", "coordinates": [ -87.689610605542356, 41.964739873592166 ] } }
]
}
