{
"type": "FeatureCollection",
"crs": { "type": "name", "properties": { "name": "urn:ogc:def:crs:OGC:1.3:CRS84" } },
"features": [
{ "type": "Feature", "id": 39003, "properties": { "SERVICE.REQUEST.TYPE": "Vacant\/Abandoned Building", "SERVICE.REQUEST.NUMBER": "13-01231861", "DATE.SERVICE.REQUEST.WAS.RECEIVED": "2013-08-27", "LOCATION.OF.BUILDING.ON.THE.LOT..IF.GARAGE..CHANGE.TYPE.CODE.TO.BGD..": "Rear", "IS.THE.BUILDING.DANGEROUS.OR.HAZARDOUS.": "", "IS.BUILDING.OPEN.OR.BOARDED.": "Boarded", "IF.THE.BUILDING.IS.OPEN..WHERE.IS.THE.ENTRY.POINT.": "", "IS.THE.BUILDING.CURRENTLY.VACANT.OR.OCCUPIED.": "Vacant", "IS.THE.BUILDING.VACANT.DUE.TO.FIRE.": "false", "ANY.PEOPLE.USING.PROPERTY...HOMELESS..CHILDEN..GANGS.": "false", "ADDRESS.STREET.NUMBER": "5217", "ADDRESS.STREET.DIRECTION": "S", "ADDRESS.STREET.NAME": "UNIVERSITY", "ADDRESS.STREET.SUFFIX": "AVE", "ZIP.CODE": 60615, "Ward": 4, "Police.District": 2, "Community.Area": 41, "FULL_ADDR": "5217 S UNIVERSITY AVE", "HOUSE_LOW": 5217, "HOUSE_HIGH": 5217, "PRE": "S", "STREET_NAME": "UNIVERSITY", "STREET_TYPE": "AVE", "SUFDIR": " ", "XCOORD": 1184733.1640209709, "YCOORD": 1870704.986166429, "STATUS1": "VALID", "STATUS2": "ACTUAL", "longitude": -87.598051003333879, "latitude": 41.800376063637252 }, "geometry": { "type": "Point", "coordinates": [ -87.598051003333879, 41.800376063637252 ] } }
]
}
