{
"type": "FeatureCollection",
"crs": { "type": "name", "properties": { "name": "urn:ogc:def:crs:OGC:1.3:CRS84" } },
"features": [
{ "type": "Feature", "id": 3273, "properties": { "SERVICE.REQUEST.TYPE": "Vacant\/Abandoned Building", "SERVICE.REQUEST.NUMBER": "10-01210921", "DATE.SERVICE.REQUEST.WAS.RECEIVED": "2010-08-02", "LOCATION.OF.BUILDING.ON.THE.LOT..IF.GARAGE..CHANGE.TYPE.CODE.TO.BGD..": "Front", "IS.THE.BUILDING.DANGEROUS.OR.HAZARDOUS.": "", "IS.BUILDING.OPEN.OR.BOARDED.": "Open", "IF.THE.BUILDING.IS.OPEN..WHERE.IS.THE.ENTRY.POINT.": "FRONT DOOR", "IS.THE.BUILDING.CURRENTLY.VACANT.OR.OCCUPIED.": "Vacant", "IS.THE.BUILDING.VACANT.DUE.TO.FIRE.": "false", "ANY.PEOPLE.USING.PROPERTY...HOMELESS..CHILDEN..GANGS.": "true", "ADDRESS.STREET.NUMBER": "1498", "ADDRESS.STREET.DIRECTION": "E", "ADDRESS.STREET.NAME": "55TH", "ADDRESS.STREET.SUFFIX": "PL", "ZIP.CODE": 60637, "Ward": 5, "Police.District": 21, "Community.Area": 41, "FULL_ADDR": "1466 E 55TH PL", "HOUSE_LOW": 1466, "HOUSE_HIGH": 1466, "PRE": "E", "STREET_NAME": "55TH", "STREET_TYPE": "PL", "SUFDIR": " ", "XCOORD": 1187121.3186377094, "YCOORD": 1868821.4670952267, "STATUS1": "VALID", "STATUS2": "LOGICAL", "longitude": -87.58935281396171, "latitude": 41.795151156950631 }, "geometry": { "type": "Point", "coordinates": [ -87.58935281396171, 41.795151156950631 ] } },
{ "type": "Feature", "id": 32626, "properties": { "SERVICE.REQUEST.TYPE": "Vacant\/Abandoned Building", "SERVICE.REQUEST.NUMBER": "13-00051183", "DATE.SERVICE.REQUEST.WAS.RECEIVED": "2013-01-14", "LOCATION.OF.BUILDING.ON.THE.LOT..IF.GARAGE..CHANGE.TYPE.CODE.TO.BGD..": "", "IS.THE.BUILDING.DANGEROUS.OR.HAZARDOUS.": "", "IS.BUILDING.OPEN.OR.BOARDED.": "", "IF.THE.BUILDING.IS.OPEN..WHERE.IS.THE.ENTRY.POINT.": "", "IS.THE.BUILDING.CURRENTLY.VACANT.OR.OCCUPIED.": "", "IS.THE.BUILDING.VACANT.DUE.TO.FIRE.": "", "ANY.PEOPLE.USING.PROPERTY...HOMELESS..CHILDEN..GANGS.": "", "ADDRESS.STREET.NUMBER": "5238", "ADDRESS.STREET.DIRECTION": "S", "ADDRESS.STREET.NAME": "HARPER", "ADDRESS.STREET.SUFFIX": "AVE", "ZIP.CODE": 60615, "Ward": 4, "Police.District": 2, "Community.Area": 41, "FULL_ADDR": "5238 S HARPER AVE", "HOUSE_LOW": 5238, "HOUSE_HIGH": 5238, "PRE": "S", "STREET_NAME": "HARPER", "STREET_TYPE": "AVE", "SUFDIR": " ", "XCOORD": 1187135.3611270422, "YCOORD": 1870509.4187303064, "STATUS1": "VALID", "STATUS2": "ACTUAL", "longitude": -87.58924774231798, "latitude": 41.79978268692367 }, "geometry": { "type": "Point", "coordinates": [ -87.58924774231798, 41.79978268692367 ] } },
{ "type": "Feature", "id": 49087, "properties": { "SERVICE.REQUEST.TYPE": "Vacant\/Abandoned Building", "SERVICE.REQUEST.NUMBER": "15-02446632", "DATE.SERVICE.REQUEST.WAS.RECEIVED": "2015-06-03", "LOCATION.OF.BUILDING.ON.THE.LOT..IF.GARAGE..CHANGE.TYPE.CODE.TO.BGD..": "Front", "IS.THE.BUILDING.DANGEROUS.OR.HAZARDOUS.": "", "IS.BUILDING.OPEN.OR.BOARDED.": "Open", "IF.THE.BUILDING.IS.OPEN..WHERE.IS.THE.ENTRY.POINT.": "FRONT", "IS.THE.BUILDING.CURRENTLY.VACANT.OR.OCCUPIED.": "Vacant", "IS.THE.BUILDING.VACANT.DUE.TO.FIRE.": "false", "ANY.PEOPLE.USING.PROPERTY...HOMELESS..CHILDEN..GANGS.": "false", "ADDRESS.STREET.NUMBER": "1451", "ADDRESS.STREET.DIRECTION": "E", "ADDRESS.STREET.NAME": "55TH", "ADDRESS.STREET.SUFFIX": "ST", "ZIP.CODE": 60615, "Ward": 5, "Police.District": 2, "Community.Area": 41, "FULL_ADDR": "1451 E 55TH ST", "HOUSE_LOW": 1451, "HOUSE_HIGH": 1451, "PRE": "E", "STREET_NAME": "55TH", "STREET_TYPE": "ST", "SUFDIR": " ", "XCOORD": 1187058.6213127316, "YCOORD": 1868912.4883571614, "STATUS1": "VALID", "STATUS2": "ACTUAL", "longitude": -87.589579834497684, "latitude": 41.795402414852255 }, "geometry": { "type": "Point", "coordinates": [ -87.589579834497684, 41.795402414852255 ] } }
]
}
