{
"type": "FeatureCollection",
"crs": { "type": "name", "properties": { "name": "urn:ogc:def:crs:OGC:1.3:CRS84" } },
"features": [
{ "type": "Feature", "id": 7529, "properties": { "SERVICE.REQUEST.TYPE": "Vacant\/Abandoned Building", "SERVICE.REQUEST.NUMBER": "11-00149283", "DATE.SERVICE.REQUEST.WAS.RECEIVED": "2011-01-31", "LOCATION.OF.BUILDING.ON.THE.LOT..IF.GARAGE..CHANGE.TYPE.CODE.TO.BGD..": "", "IS.THE.BUILDING.DANGEROUS.OR.HAZARDOUS.": "", "IS.BUILDING.OPEN.OR.BOARDED.": "", "IF.THE.BUILDING.IS.OPEN..WHERE.IS.THE.ENTRY.POINT.": "", "IS.THE.BUILDING.CURRENTLY.VACANT.OR.OCCUPIED.": "", "IS.THE.BUILDING.VACANT.DUE.TO.FIRE.": "", "ANY.PEOPLE.USING.PROPERTY...HOMELESS..CHILDEN..GANGS.": "", "ADDRESS.STREET.NUMBER": "1939", "ADDRESS.STREET.DIRECTION": "W", "ADDRESS.STREET.NAME": "CORNELIA", "ADDRESS.STREET.SUFFIX": "AVE", "ZIP.CODE": 60657, "Ward": 32, "Police.District": 19, "Community.Area": 5, "FULL_ADDR": "1939 W CORNELIA AVE", "HOUSE_LOW": 1939, "HOUSE_HIGH": 1939, "PRE": "W", "STREET_NAME": "CORNELIA", "STREET_TYPE": "AVE", "SUFDIR": " ", "XCOORD": 1162633.0073258327, "YCOORD": 1923206.5689893141, "STATUS1": "VALID", "STATUS2": "ACTUAL", "longitude": -87.677628206161017, "latitude": 41.944935290765564 }, "geometry": { "type": "Point", "coordinates": [ -87.677628206161017, 41.944935290765571 ] } },
{ "type": "Feature", "id": 28440, "properties": { "SERVICE.REQUEST.TYPE": "Vacant\/Abandoned Building", "SERVICE.REQUEST.NUMBER": "12-01292464", "DATE.SERVICE.REQUEST.WAS.RECEIVED": "2012-07-19", "LOCATION.OF.BUILDING.ON.THE.LOT..IF.GARAGE..CHANGE.TYPE.CODE.TO.BGD..": "Rear", "IS.THE.BUILDING.DANGEROUS.OR.HAZARDOUS.": "", "IS.BUILDING.OPEN.OR.BOARDED.": "Boarded", "IF.THE.BUILDING.IS.OPEN..WHERE.IS.THE.ENTRY.POINT.": "", "IS.THE.BUILDING.CURRENTLY.VACANT.OR.OCCUPIED.": "Vacant", "IS.THE.BUILDING.VACANT.DUE.TO.FIRE.": "false", "ANY.PEOPLE.USING.PROPERTY...HOMELESS..CHILDEN..GANGS.": "false", "ADDRESS.STREET.NUMBER": "1823", "ADDRESS.STREET.DIRECTION": "W", "ADDRESS.STREET.NAME": "CORNELIA", "ADDRESS.STREET.SUFFIX": "AVE", "ZIP.CODE": 60657, "Ward": 32, "Police.District": 19, "Community.Area": 5, "FULL_ADDR": "1823 W CORNELIA AVE", "HOUSE_LOW": 1823, "HOUSE_HIGH": 1823, "PRE": "W", "STREET_NAME": "CORNELIA", "STREET_TYPE": "AVE", "SUFDIR": " ", "XCOORD": 1163382.4703388447, "YCOORD": 1923224.2957920732, "STATUS1": "VALID", "STATUS2": "ACTUAL", "longitude": -87.674872984381693, "latitude": 41.944968168614587 }, "geometry": { "type": "Point", "coordinates": [ -87.674872984381693, 41.944968168614587 ] } }
]
}
