{
"type": "FeatureCollection",
"crs": { "type": "name", "properties": { "name": "urn:ogc:def:crs:OGC:1.3:CRS84" } },
"features": [
{ "type": "Feature", "id": 47552, "properties": { "SERVICE.REQUEST.TYPE": "Vacant\/Abandoned Building", "SERVICE.REQUEST.NUMBER": "14-02204769", "DATE.SERVICE.REQUEST.WAS.RECEIVED": "2014-12-29", "LOCATION.OF.BUILDING.ON.THE.LOT..IF.GARAGE..CHANGE.TYPE.CODE.TO.BGD..": "", "IS.THE.BUILDING.DANGEROUS.OR.HAZARDOUS.": "", "IS.BUILDING.OPEN.OR.BOARDED.": "", "IF.THE.BUILDING.IS.OPEN..WHERE.IS.THE.ENTRY.POINT.": "", "IS.THE.BUILDING.CURRENTLY.VACANT.OR.OCCUPIED.": "", "IS.THE.BUILDING.VACANT.DUE.TO.FIRE.": "", "ANY.PEOPLE.USING.PROPERTY...HOMELESS..CHILDEN..GANGS.": "", "ADDRESS.STREET.NUMBER": "2042", "ADDRESS.STREET.DIRECTION": "N", "ADDRESS.STREET.NAME": "CLIFTON", "ADDRESS.STREET.SUFFIX": "AVE", "ZIP.CODE": 60614, "Ward": 43, "Police.District": 18, "Community.Area": 7, "FULL_ADDR": "2042 N CLIFTON AVE", "HOUSE_LOW": 2042, "HOUSE_HIGH": 2042, "PRE": "N", "STREET_NAME": "CLIFTON", "STREET_TYPE": "AVE", "SUFDIR": " ", "XCOORD": 1168264.8855517504, "YCOORD": 1913916.6214604948, "STATUS1": "VALID", "STATUS2": "ACTUAL", "longitude": -87.65719704927578, "latitude": 41.919323128353064 }, "geometry": { "type": "Point", "coordinates": [ -87.65719704927578, 41.919323128353064 ] } }
]
}
