{
"type": "FeatureCollection",
"crs": { "type": "name", "properties": { "name": "urn:ogc:def:crs:OGC:1.3:CRS84" } },
"features": [
{ "type": "Feature", "id": 41868, "properties": { "SERVICE.REQUEST.TYPE": "Vacant\/Abandoned Building", "SERVICE.REQUEST.NUMBER": "14-00436529", "DATE.SERVICE.REQUEST.WAS.RECEIVED": "2014-03-27", "LOCATION.OF.BUILDING.ON.THE.LOT..IF.GARAGE..CHANGE.TYPE.CODE.TO.BGD..": "Front", "IS.THE.BUILDING.DANGEROUS.OR.HAZARDOUS.": "", "IS.BUILDING.OPEN.OR.BOARDED.": "Open", "IF.THE.BUILDING.IS.OPEN..WHERE.IS.THE.ENTRY.POINT.": "", "IS.THE.BUILDING.CURRENTLY.VACANT.OR.OCCUPIED.": "Vacant", "IS.THE.BUILDING.VACANT.DUE.TO.FIRE.": "false", "ANY.PEOPLE.USING.PROPERTY...HOMELESS..CHILDEN..GANGS.": "false", "ADDRESS.STREET.NUMBER": "520", "ADDRESS.STREET.DIRECTION": "W", "ADDRESS.STREET.NAME": "GRANT", "ADDRESS.STREET.SUFFIX": "PL", "ZIP.CODE": 60614, "Ward": 43, "Police.District": 18, "Community.Area": 7, "FULL_ADDR": "520 W GRANT PL", "HOUSE_LOW": 520, "HOUSE_HIGH": 520, "PRE": "W", "STREET_NAME": "GRANT", "STREET_TYPE": "PL", "SUFDIR": " ", "XCOORD": 1172316.855567904, "YCOORD": 1915262.7950750459, "STATUS1": "VALID", "STATUS2": "ACTUAL", "longitude": -87.64226984356759, "latitude": 41.922928461822636 }, "geometry": { "type": "Point", "coordinates": [ -87.64226984356759, 41.922928461822636 ] } }
]
}
