{
"type": "FeatureCollection",
"crs": { "type": "name", "properties": { "name": "urn:ogc:def:crs:OGC:1.3:CRS84" } },
"features": [
{ "type": "Feature", "id": 21586, "properties": { "SERVICE.REQUEST.TYPE": "Vacant\/Abandoned Building", "SERVICE.REQUEST.NUMBER": "11-04259404", "DATE.SERVICE.REQUEST.WAS.RECEIVED": "2011-12-15", "LOCATION.OF.BUILDING.ON.THE.LOT..IF.GARAGE..CHANGE.TYPE.CODE.TO.BGD..": "", "IS.THE.BUILDING.DANGEROUS.OR.HAZARDOUS.": "", "IS.BUILDING.OPEN.OR.BOARDED.": "", "IF.THE.BUILDING.IS.OPEN..WHERE.IS.THE.ENTRY.POINT.": "", "IS.THE.BUILDING.CURRENTLY.VACANT.OR.OCCUPIED.": "", "IS.THE.BUILDING.VACANT.DUE.TO.FIRE.": "", "ANY.PEOPLE.USING.PROPERTY...HOMELESS..CHILDEN..GANGS.": "", "ADDRESS.STREET.NUMBER": "1701", "ADDRESS.STREET.DIRECTION": "N", "ADDRESS.STREET.NAME": "MOHAWK", "ADDRESS.STREET.SUFFIX": "ST", "ZIP.CODE": 60614, "Ward": 43, "Police.District": 18, "Community.Area": 7, "FULL_ADDR": "1701 N MOHAWK ST", "HOUSE_LOW": 1701, "HOUSE_HIGH": 1701, "PRE": "N", "STREET_NAME": "MOHAWK", "STREET_TYPE": "ST", "SUFDIR": " ", "XCOORD": 1172380.6462255607, "YCOORD": 1911616.7643477144, "STATUS1": "VALID", "STATUS2": "ACTUAL", "longitude": -87.6421434290707, "latitude": 41.912922169145936 }, "geometry": { "type": "Point", "coordinates": [ -87.6421434290707, 41.912922169145943 ] } }
]
}
