{
"type": "FeatureCollection",
"crs": { "type": "name", "properties": { "name": "urn:ogc:def:crs:OGC:1.3:CRS84" } },
"features": [
{ "type": "Feature", "id": 5026, "properties": { "SERVICE.REQUEST.TYPE": "Vacant\/Abandoned Building", "SERVICE.REQUEST.NUMBER": "10-01662911", "DATE.SERVICE.REQUEST.WAS.RECEIVED": "2010-10-13", "LOCATION.OF.BUILDING.ON.THE.LOT..IF.GARAGE..CHANGE.TYPE.CODE.TO.BGD..": "Front", "IS.THE.BUILDING.DANGEROUS.OR.HAZARDOUS.": "", "IS.BUILDING.OPEN.OR.BOARDED.": "Open", "IF.THE.BUILDING.IS.OPEN..WHERE.IS.THE.ENTRY.POINT.": "OPEN", "IS.THE.BUILDING.CURRENTLY.VACANT.OR.OCCUPIED.": "Vacant", "IS.THE.BUILDING.VACANT.DUE.TO.FIRE.": "false", "ANY.PEOPLE.USING.PROPERTY...HOMELESS..CHILDEN..GANGS.": "false", "ADDRESS.STREET.NUMBER": "1919", "ADDRESS.STREET.DIRECTION": "N", "ADDRESS.STREET.NAME": "BURLING", "ADDRESS.STREET.SUFFIX": "ST", "ZIP.CODE": 60614, "Ward": 43, "Police.District": 18, "Community.Area": 7, "FULL_ADDR": "1919 N BURLING ST", "HOUSE_LOW": 1919, "HOUSE_HIGH": 1919, "PRE": "N", "STREET_NAME": "BURLING", "STREET_TYPE": "ST", "SUFDIR": " ", "XCOORD": 1171018.0184978845, "YCOORD": 1912958.1256606432, "STATUS1": "VALID", "STATUS2": "ACTUAL", "longitude": -87.647109931812665, "latitude": 41.9166329581791 }, "geometry": { "type": "Point", "coordinates": [ -87.647109931812665, 41.916632958179108 ] } }
]
}
