{
"type": "FeatureCollection",
"crs": { "type": "name", "properties": { "name": "urn:ogc:def:crs:OGC:1.3:CRS84" } },
"features": [
{ "type": "Feature", "id": 12709, "properties": { "SERVICE.REQUEST.TYPE": "Vacant\/Abandoned Building", "SERVICE.REQUEST.NUMBER": "11-02377809", "DATE.SERVICE.REQUEST.WAS.RECEIVED": "2011-06-01", "LOCATION.OF.BUILDING.ON.THE.LOT..IF.GARAGE..CHANGE.TYPE.CODE.TO.BGD..": "", "IS.THE.BUILDING.DANGEROUS.OR.HAZARDOUS.": "", "IS.BUILDING.OPEN.OR.BOARDED.": "", "IF.THE.BUILDING.IS.OPEN..WHERE.IS.THE.ENTRY.POINT.": "", "IS.THE.BUILDING.CURRENTLY.VACANT.OR.OCCUPIED.": "", "IS.THE.BUILDING.VACANT.DUE.TO.FIRE.": "", "ANY.PEOPLE.USING.PROPERTY...HOMELESS..CHILDEN..GANGS.": "", "ADDRESS.STREET.NUMBER": "2951", "ADDRESS.STREET.DIRECTION": "S", "ADDRESS.STREET.NAME": "MICHIGAN", "ADDRESS.STREET.SUFFIX": "AVE", "ZIP.CODE": 60616, "Ward": 2, "Police.District": 21, "Community.Area": 35, "FULL_ADDR": "2951 S MICHIGAN AVE", "HOUSE_LOW": 2951, "HOUSE_HIGH": 2951, "PRE": "S", "STREET_NAME": "MICHIGAN", "STREET_TYPE": "AVE", "SUFDIR": " ", "XCOORD": 1177778.9072858724, "YCOORD": 1885265.3142696277, "STATUS1": "VALID", "STATUS2": "ACTUAL", "longitude": -87.623112805431887, "latitude": 41.840491225981438 }, "geometry": { "type": "Point", "coordinates": [ -87.623112805431887, 41.840491225981438 ] } }
]
}
